{
  "doc_type": "competitor",
  "slug": "2026-05-06-romel-car-house",
  "name": "romel-car-house",
  "sector": "automotive-car-care",
  "frontmatter": {
    "entity_type": "competitor",
    "sector": "automotive-car-care",
    "entity_slug": "2026-05-06-romel-car-house",
    "last_verified_at": "2026-06-25T12:00:00Z",
    "freshness_status": "fresh",
    "confidence_score": "0.50",
    "primary_sources": "- []"
  },
  "profile_category": "",
  "entity_slug": "2026-05-06-romel-car-house",
  "last_verified_at": "2026-06-25T12:00:00Z",
  "freshness_status": "fresh",
  "confidence_score": 0.5,
  "strengths": [
    "1. **108K followers** — largest reconditioned car dealer on Facebook BD",
    "2. **Bank loan & finance options** — massive enabler for BD market where most buyers need financing",
    "3. **Test drive availability** — \"Book your test drive any time\"",
    "4. **Always open** — aggressive availability",
    "5. **100% recommendation** — trust signal",
    "6. **LinkedIn presence** — professional networking for corporate clients"
  ],
  "weaknesses": [
    "1. **No product ecosystem** — no car care products, no accessories, no aftercare",
    "2. **No website** — Facebook-only presence",
    "3. **No guarantees/warranties** visible",
    "4. **No blog/SEO** — invisible on Google",
    "5. **Car sales only** — no recurring revenue model"
  ],
  "threat_level": "",
  "threat_overlap_score": null,
  "pricing_signals": [
    {
      "item": "*TODO*",
      "value": "*Research needed*",
      "date": "2026-06",
      "source": ""
    }
  ],
  "customer_segments": [],
  "operations_notes": "*TODO: Research from BD market sources*\n\n---",
  "financial_signals": "| Metric | Detail |\n|--------|--------|\n| *TODO* | *Research needed* |\n\n---",
  "sentiment_summary": "*TODO: Research from BD market sources*\n\n---",
  "compliance_notes": "*TODO: Research from BD market sources*\n\n---",
  "evidence_sources": [
    "*TODO: Add verifiable sources*"
  ],
  "file_path": "sectors/automotive-car-care/bd-market/competitors/2026-05-06-romel-car-house.md"
}